spreadsheet_column_splitter/__init__.py
spreadsheet_column_splitter/functions.py
spreadsheet_column_splitter/splitter.py
spreadsheet_column_splitter-0.1.2.dist-info/licenses/LICENSE
spreadsheet_column_splitter-0.1.2.dist-info/WHEEL
spreadsheet_column_splitter-0.1.2.dist-info/METADATA
spreadsheet_column_splitter-0.1.2.dist-info/RECORD
