Metadata-Version: 2.4
Name: spreadsheet-column-splitter
Version: 0.1.2
Summary: Group and split a csv or Excel into separate files based on data in a column.
Author: Marc Brodeur
Author-email: Marc Brodeur <github.n2hj4@simplelogin.com>
License-Expression: MIT
License-File: LICENSE
Classifier: Programming Language :: Python :: 3
Classifier: Operating System :: OS Independent
Requires-Dist: openpyxl>=3.1.5
Requires-Dist: pandas>=2.3.3
Requires-Python: >=3.12
Project-URL: Homepage, https://github.com/mrbrodeur/spreadsheet_column_splitter
Project-URL: Source, https://github.com/mrbrodeur/spreadsheet_column_splitter
